MANIFEST.in
README.md
setup.py
version.txt
doc/description.txt
fsc.export.egg-info/PKG-INFO
fsc.export.egg-info/SOURCES.txt
fsc.export.egg-info/dependency_links.txt
fsc.export.egg-info/requires.txt
fsc.export.egg-info/top_level.txt
fsc/export/__init__.py
fsc/export/_export.py
fsc/export/_version.py
fsc/export/py.typed
fsc/export/version.txt